oriole_api/__init__.py
oriole_api/json.py
oriole_api/main.py
oriole_api/pyramid.py
oriole_api-5.0.0.dist-info/AUTHORS.rst
oriole_api-5.0.0.dist-info/LICENSE
oriole_api-5.0.0.dist-info/METADATA
oriole_api-5.0.0.dist-info/WHEEL
oriole_api-5.0.0.dist-info/top_level.txt
oriole_api-5.0.0.dist-info/zip-safe
oriole_api-5.0.0.dist-info/RECORD
